sirp_dsi_converter/__init__.py
sirp_dsi_converter/app.py
sirp_dsi_converter/conversion.py
sirp_dsi_converter/experimental.py
sirp_dsi_converter/transformation.py
sirp_dsi_converter/update_sirp_components.py
sirp_dsi_converter/cache/sirp_cache.json
sirp_dsi_converter/cache/SI_Digital_Framework/LICENCE
sirp_dsi_converter/cache/SI_Digital_Framework/SI_Reference_Point/TTL/bodies.ttl
sirp_dsi_converter/cache/SI_Digital_Framework/SI_Reference_Point/TTL/cctf.ttl
sirp_dsi_converter/cache/SI_Digital_Framework/SI_Reference_Point/TTL/cgpm.ttl
sirp_dsi_converter/cache/SI_Digital_Framework/SI_Reference_Point/TTL/cipm.ttl
sirp_dsi_converter/cache/SI_Digital_Framework/SI_Reference_Point/TTL/constants.ttl
sirp_dsi_converter/cache/SI_Digital_Framework/SI_Reference_Point/TTL/decisions.ttl
sirp_dsi_converter/cache/SI_Digital_Framework/SI_Reference_Point/TTL/prefixes.ttl
sirp_dsi_converter/cache/SI_Digital_Framework/SI_Reference_Point/TTL/quantities.ttl
sirp_dsi_converter/cache/SI_Digital_Framework/SI_Reference_Point/TTL/si.ttl
sirp_dsi_converter/cache/SI_Digital_Framework/SI_Reference_Point/TTL/units.ttl
sirp_dsi_converter-1.2.0b0.dist-info/LICENSE
sirp_dsi_converter-1.2.0b0.dist-info/METADATA
sirp_dsi_converter-1.2.0b0.dist-info/WHEEL
sirp_dsi_converter-1.2.0b0.dist-info/top_level.txt
sirp_dsi_converter-1.2.0b0.dist-info/RECORD
