Metadata-Version: 2.2
Name: sirp_dsi_converter
Version: 1.2.0b0
Summary: A converter between D-SI and SI Reference Point unit formats
Author: Diego Nahuel Coppa, Daniel Hutzschenreuter, Maximilian Gruber
Maintainer-email: Maximilian Gruber <maximilian.gruber@ptb.de>
License: MIT License
Project-URL: Homepage, https://github.com/PTB-M4D/SIRP-D-SI-Converter-Service/
Project-URL: Bug Reports, https://github.com/PTB-M4D/SIRP-D-SI-Converter-Service/issues
Project-URL: Source, https://github.com/PTB-M4D/SIRP-D-SI-Converter-Service/
Keywords: metrology,unit conversion
Classifier: Development Status :: 3 - Alpha
Classifier: Intended Audience :: Developers
Classifier: Topic :: Software Development :: Libraries
Classifier: License :: OSI Approved :: MIT License
Classifier: Programming Language :: Python :: 3
Classifier: Programming Language :: Python :: 3.9
Classifier: Programming Language :: Python :: 3.10
Classifier: Programming Language :: Python :: 3.11
Classifier: Programming Language :: Python :: 3.12
Classifier: Programming Language :: Python :: 3.13
Classifier: Programming Language :: Python :: 3 :: Only
Requires-Python: >=3.9
License-File: LICENSE
Requires-Dist: rdflib
